drf_observer/__init__.py
drf_observer/mixins.py
drf_observer/decorators.py
drf_observer-0.1.0.dist-info/metadata.json
drf_observer-0.1.0.dist-info/WHEEL
drf_observer-0.1.0.dist-info/METADATA
drf_observer-0.1.0.dist-info/DESCRIPTION.rst
drf_observer-0.1.0.dist-info/RECORD
drf_observer-0.1.0.dist-info/top_level.txt
